django3_admin_select2/__init__.py
django3_admin_select2/static/django3_admin_select2/css/select2.min.css
django3_admin_select2/static/django3_admin_select2/js/select2.min.js
django3_admin_select2/templates/admin/base_site.html
django3_admin_select2-0.1.0.dist-info/LICENSE
django3_admin_select2-0.1.0.dist-info/METADATA
django3_admin_select2-0.1.0.dist-info/WHEEL
django3_admin_select2-0.1.0.dist-info/top_level.txt
django3_admin_select2-0.1.0.dist-info/RECORD
