Metadata-Version: 2.1
Name: django3-admin-select2
Version: 0.1.0
Summary: Enable select2 for Django3 admin select inputs
Home-page: https://github.com/Medsien/django3-admin-select2
Author: Medsien, Inc.
Author-email: hello@medsien.com
License: UNKNOWN
Keywords: django,django-admin,select2
Platform: UNKNOWN
License-File: LICENSE
Requires-Dist: Django (>=3.0)
